ds_methods/__init__.py
ds_methods/common/__init__.py
ds_methods/common/constants.py
ds_methods/common/decorators.py
ds_methods/common/df.py
ds_methods/common/enums.py
ds_methods/common/types.py
ds_methods/common/utils.py
ds_methods/common/validators.py
ds_methods/methods/__init__.py
ds_methods/methods/base.py
ds_methods/methods/pipeline.py
ds_methods/methods/analysis/__init__.py
ds_methods/methods/analysis/box_plot/__init__.py
ds_methods/methods/analysis/box_plot/box_plot.py
ds_methods/methods/analysis/box_plot/schemas.py
ds_methods/methods/analysis/classification/__init__.py
ds_methods/methods/analysis/classification/random_forest/__init__.py
ds_methods/methods/analysis/classification/random_forest/random_forest.py
ds_methods/methods/analysis/classification/random_forest/schemas.py
ds_methods/methods/analysis/classification/svm/__init__.py
ds_methods/methods/analysis/classification/svm/schemas.py
ds_methods/methods/analysis/classification/svm/svm.py
ds_methods/methods/analysis/clustering/__init__.py
ds_methods/methods/analysis/clustering/k_means/__init__.py
ds_methods/methods/analysis/clustering/k_means/k_means.py
ds_methods/methods/analysis/clustering/k_means/schemas.py
ds_methods/methods/analysis/hmm/__init__.py
ds_methods/methods/analysis/hmm/hmm.py
ds_methods/methods/analysis/hmm/schemas.py
ds_methods/methods/analysis/ks_test/__init__.py
ds_methods/methods/analysis/ks_test/ks_test.py
ds_methods/methods/analysis/ks_test/schemas.py
ds_methods/methods/analysis/linear_regression/__init__.py
ds_methods/methods/analysis/linear_regression/linear_regression.py
ds_methods/methods/analysis/linear_regression/schemas.py
ds_methods/methods/analysis/pca/__init__.py
ds_methods/methods/analysis/pca/pca.py
ds_methods/methods/analysis/pca/schemas.py
ds_methods/methods/analysis/time_warping/__init__.py
ds_methods/methods/analysis/time_warping/schemas.py
ds_methods/methods/analysis/time_warping/time_warping.py
ds_methods/methods/analysis/truncated_svd/__init__.py
ds_methods-0.22.dist-info/LICENSE
ds_methods-0.22.dist-info/METADATA
ds_methods-0.22.dist-info/WHEEL
ds_methods-0.22.dist-info/top_level.txt
ds_methods-0.22.dist-info/RECORD
