Metadata-Version: 2.1
Name: ds-methods
Version: 0.22
Summary: Pipelines architecture for common data science methods and time series analysis
Home-page: https://github.com/NovosadVictor/ds_methods
Author: Victor Novosad
Author-email: v.novosad@ivpa.ru
License: MIT
Keywords: data-science analysis methods
Platform: UNKNOWN
Classifier: Programming Language :: Python :: 3.8
Classifier: License :: OSI Approved :: MIT License
Requires-Dist: numpy
Requires-Dist: pandas
Requires-Dist: schema (==0.7.2)
Requires-Dist: python-dateutil
Requires-Dist: scipy
Requires-Dist: statsmodels
Requires-Dist: scikit-learn
Requires-Dist: dtw-python
Requires-Dist: hmmlearn
Requires-Dist: matplotlib
